xaal/__init__.py
xaal/owm/__init__.py
xaal/owm/__main__.py
xaal/owm/gw.py
xaal_owm-0.3.2.dist-info/METADATA
xaal_owm-0.3.2.dist-info/WHEEL
xaal_owm-0.3.2.dist-info/top_level.txt
xaal_owm-0.3.2.dist-info/RECORD
