Metadata-Version: 2.4
Name: xaal.owm
Version: 0.3.2
Summary: xAAL devices for OpenWeather Map
Author-email: Jerome Kerdreux <Jerome.Kerdreux@imt-atlantique.fr>
License-Expression: GPL-3.0-or-later
Keywords: xaal,own,weather
Classifier: Programming Language :: Python
Classifier: Topic :: Software Development :: Libraries :: Python Modules
Requires-Dist: xaal.lib
Requires-Dist: xaal.schemas
Requires-Dist: pyowm==2.10.0
Requires-Dist: setuptools
